langchain_joungna/__init__.py
langchain_joungna/logging.py
langchain_joungna/messages.py
langchain_joungna/models.py
langchain_joungna/prompts.py
langchain_joungna-0.0.6.dist-info/METADATA
langchain_joungna-0.0.6.dist-info/WHEEL
langchain_joungna-0.0.6.dist-info/top_level.txt
langchain_joungna-0.0.6.dist-info/RECORD
